{"frames":{"bg_jpg":{"x":0,"y":0,"w":640,"h":1136,"offX":0,"offY":0,"sourceW":640,"sourceH":1136},"egret_icon_png":{"x":642,"y":0,"w":115,"h":172,"offX":0,"offY":0,"sourceW":115,"sourceH":172},"player_flappybird_3":{"x":759,"y":0,"w":34,"h":24,"offX":0,"offY":0,"sourceW":34,"sourceH":24},"player_flappybird_2":{"x":795,"y":0,"w":34,"h":24,"offX":0,"offY":0,"sourceW":34,"sourceH":24},"player_flappybird_1":{"x":831,"y":0,"w":34,"h":24,"offX":0,"offY":0,"sourceW":34,"sourceH":24}},"file":"preload-0sheet_39d55f00.png"}